opencl_fdfd/LICENSE.md
opencl_fdfd/README.md
opencl_fdfd/__init__.py
opencl_fdfd/csr.py
opencl_fdfd/main.py
opencl_fdfd/ops.py
opencl_fdfd/py.typed
opencl_fdfd/kernels/common.cl
opencl_fdfd/kernels/e2h.cl
opencl_fdfd/kernels/h2e.cl
opencl_fdfd/kernels/p2e.cl
opencl_fdfd-0.4.dist-info/METADATA
opencl_fdfd-0.4.dist-info/WHEEL
opencl_fdfd-0.4.dist-info/licenses/LICENSE.md
opencl_fdfd-0.4.dist-info/RECORD
