Metadata-Version: 2.1
Name: opencl_fdfd
Version: 0.4
Summary: OpenCL FDFD solver
Author-email: Jan Petykiewicz <jan@mpxd.net>
License: GNU Affero General Public License
License-File: LICENSE.md
Keywords: FDFD,FDTD,PML,dielectric,difference,domain,electromagnetic,finite,frequency,optics,simulation,solver
Classifier: Development Status :: 4 - Beta
Classifier: Intended Audience :: Developers
Classifier: Intended Audience :: Manufacturing
Classifier: Intended Audience :: Science/Research
Classifier: License :: OSI Approved :: GNU Affero General Public License v3
Classifier: Programming Language :: Python :: 3
Classifier: Topic :: Scientific/Engineering
Requires-Python: >=3.8
Requires-Dist: jinja2
Requires-Dist: meanas>=0.5
Requires-Dist: numpy~=1.21
Requires-Dist: pyopencl
